signal_processing_algorithms/gesd.py
signal_processing_algorithms/__init__.py
signal_processing_algorithms/determinism.py
signal_processing_algorithms/energy_statistics/e_divisive.c
signal_processing_algorithms/energy_statistics/__init__.py
signal_processing_algorithms/energy_statistics/_e_divisive.cpython-311-x86_64-linux-gnu.so
signal_processing_algorithms/energy_statistics/cext_calculator.py
signal_processing_algorithms/energy_statistics/energy_statistics.py
signal_processing_algorithms-2.1.6.dist-info/RECORD
signal_processing_algorithms-2.1.6.dist-info/LICENSE
signal_processing_algorithms-2.1.6.dist-info/METADATA
signal_processing_algorithms-2.1.6.dist-info/WHEEL
