Metadata-Version: 2.1
Name: signal-processing-algorithms
Version: 2.1.6
Summary: Signal Processing Algorithms from MongoDB
Home-page: https://github.com/mongodb/signal-processing-algorithms
License: Apache-2.0
Author: Alexander Costas
Author-email: alexander.costas@mongodb.com
Requires-Python: >=3.11,<3.12
Classifier: License :: OSI Approved :: Apache Software License
Classifier: Programming Language :: Python :: 3
Classifier: Programming Language :: Python :: 3.11
Requires-Dist: gevent (>=24.10.1,<25.0.0)
Requires-Dist: more-itertools (>=8.2.0,<9.0.0)
Requires-Dist: numpy (>=1.24.4,<2.0.0)
Requires-Dist: pyyaml (>=6.0.0,<7.0.0)
Requires-Dist: scipy (>=1.8.1,<2.0.0)
Requires-Dist: setuptools (>=65.5.1,<71.0.0)
Requires-Dist: structlog (>=24.2,<25.0)
Requires-Dist: typing-extensions (>=4.5.0,<5.0.0)
Project-URL: Repository, https://github.com/mongodb/signal-processing-algorithms
